LICENSE
MANIFEST.in
README.md
setup.cfg
setup.py
deathFriends/__init__.py
deathFriends/__main__.py
deathFriends/bullet.py
deathFriends/camera.py
deathFriends/game.py
deathFriends/mapAll.py
deathFriends/player.py
deathFriends/settings.py
deathFriends/tilemap.py
deathFriends/wall.py
deathFriends.egg-info/PKG-INFO
deathFriends.egg-info/SOURCES.txt
deathFriends.egg-info/dependency_links.txt
deathFriends.egg-info/entry_points.txt
deathFriends.egg-info/requires.txt
deathFriends.egg-info/top_level.txt
deathFriends/fonts/Prototype.ttf
deathFriends/fonts/begok.ttf
deathFriends/sprints/death.png
deathFriends/sprints/fundo.jpg
deathFriends/sprints/gun.png
deathFriends/sprints/player.png
deathFriends/sprints/wall.png