Metadata-Version: 2.1
Name: deathFriends
Version: 0.0.5
Summary: Jogo de tiro multiplayer
Home-page: https://github.com/albertosilv/deathFriends
Author: José Alberto
Author-email: jose.alberto.silva@ccc.ufcg.edu.br
License: MIT License
Keywords: game,jogo,multiplayer,ação,tiro,online
Platform: UNKNOWN
Requires-Python: >=3.6
